{"generated_at":"2026-07-20T07:14:55+00:00","window_minutes":15,"counts":{"total":87,"g19":74,"g18":13},"source":"NOAA GOES-R GLM L2 LCFA via NOAA Open Data on AWS S3 (public, no auth)","flashes":[{"lat":3.4762,"lng":-128.2003,"energy_fJ":2268.3,"sat":"g19","age_sec":898,"type":"flash"},{"lat":36.7941,"lng":-70.8939,"energy_fJ":1540.3,"sat":"g19","age_sec":899,"type":"flash"},{"lat":35.1219,"lng":-73.1809,"energy_fJ":1409.3,"sat":"g19","age_sec":900,"type":"flash"},{"lat":52.0643,"lng":-89.274,"energy_fJ":1251.3,"sat":"g19","age_sec":899,"type":"flash"},{"lat":30.5233,"lng":-109.6897,"energy_fJ":895.3,"sat":"g19","age_sec":897,"type":"flash"},{"lat":35.1578,"lng":-73.1982,"energy_fJ":687.3,"sat":"g19","age_sec":899,"type":"flash"},{"lat":25.4793,"lng":-87.2239,"energy_fJ":671.3,"sat":"g19","age_sec":900,"type":"flash"},{"lat":25.4792,"lng":-87.1235,"energy_fJ":466.3,"sat":"g18","age_sec":900,"type":"flash"},{"lat":30.5143,"lng":-109.6719,"energy_fJ":421.3,"sat":"g18","age_sec":897,"type":"flash"},{"lat":35.4527,"lng":-72.7507,"energy_fJ":375.3,"sat":"g19","age_sec":899,"type":"flash"},{"lat":-21.309,"lng":-121.7846,"energy_fJ":355.3,"sat":"g19","age_sec":899,"type":"flash"},{"lat":-30.1866,"lng":-57.1061,"energy_fJ":336.3,"sat":"g19","age_sec":899,"type":"flash"},{"lat":44.5157,"lng":-95.0855,"energy_fJ":317.3,"sat":"g18","age_sec":898,"type":"flash"},{"lat":-29.4352,"lng":-58.1619,"energy_fJ":269.3,"sat":"g19","age_sec":899,"type":"flash"},{"lat":44.5006,"lng":-95.2149,"energy_fJ":268.3,"sat":"g19","age_sec":898,"type":"flash"},{"lat":24.6173,"lng":-108.3481,"energy_fJ":268.3,"sat":"g18","age_sec":898,"type":"flash"},{"lat":-28.5833,"lng":-56.0953,"energy_fJ":260.3,"sat":"g19","age_sec":898,"type":"flash"},{"lat":34.8979,"lng":-80.5314,"energy_fJ":245.3,"sat":"g19","age_sec":899,"type":"flash"},{"lat":35.1777,"lng":-72.9632,"energy_fJ":243.3,"sat":"g19","age_sec":898,"type":"flash"},{"lat":-28.3178,"lng":-56.9805,"energy_fJ":239.3,"sat":"g19","age_sec":899,"type":"flash"},{"lat":-29.0804,"lng":-57.4312,"energy_fJ":234.3,"sat":"g19","age_sec":897,"type":"flash"},{"lat":34.7534,"lng":-79.8858,"energy_fJ":228.3,"sat":"g19","age_sec":900,"type":"flash"},{"lat":10.3657,"lng":-81.787,"energy_fJ":217.3,"sat":"g19","age_sec":899,"type":"flash"},{"lat":10.2188,"lng":-80.3551,"energy_fJ":208.3,"sat":"g19","age_sec":898,"type":"flash"},{"lat":51.0642,"lng":-91.8695,"energy_fJ":207.3,"sat":"g19","age_sec":900,"type":"flash"},{"lat":8.4452,"lng":-84.238,"energy_fJ":176.3,"sat":"g18","age_sec":896,"type":"flash"},{"lat":-28.5291,"lng":-56.3555,"energy_fJ":158.3,"sat":"g19","age_sec":899,"type":"flash"},{"lat":51.0867,"lng":-88.9895,"energy_fJ":128.3,"sat":"g19","age_sec":899,"type":"flash"},{"lat":7.6527,"lng":-67.1085,"energy_fJ":112.3,"sat":"g19","age_sec":898,"type":"flash"},{"lat":24.6186,"lng":-108.3965,"energy_fJ":100.3,"sat":"g19","age_sec":898,"type":"flash"},{"lat":-29.8016,"lng":-53.2682,"energy_fJ":97.3,"sat":"g19","age_sec":899,"type":"flash"},{"lat":35.6327,"lng":-74.1435,"energy_fJ":91.3,"sat":"g19","age_sec":900,"type":"flash"},{"lat":-27.8834,"lng":-53.2153,"energy_fJ":83.3,"sat":"g19","age_sec":899,"type":"flash"},{"lat":-28.1498,"lng":-57.4904,"energy_fJ":76.3,"sat":"g19","age_sec":898,"type":"flash"},{"lat":28.8181,"lng":-89.6615,"energy_fJ":75.3,"sat":"g19","age_sec":898,"type":"flash"},{"lat":35.4775,"lng":-74.0129,"energy_fJ":70.3,"sat":"g19","age_sec":897,"type":"flash"},{"lat":-29.2976,"lng":-57.8269,"energy_fJ":70.3,"sat":"g19","age_sec":897,"type":"flash"},{"lat":36.7841,"lng":-70.8595,"energy_fJ":66.3,"sat":"g19","age_sec":898,"type":"flash"},{"lat":17.1957,"lng":-109.1876,"energy_fJ":66.3,"sat":"g18","age_sec":897,"type":"flash"},{"lat":-28.1743,"lng":-55.317,"energy_fJ":64.3,"sat":"g19","age_sec":900,"type":"flash"},{"lat":35.5855,"lng":-74.1382,"energy_fJ":57.3,"sat":"g19","age_sec":898,"type":"flash"},{"lat":-28.117,"lng":-56.3381,"energy_fJ":55.3,"sat":"g19","age_sec":898,"type":"flash"},{"lat":-28.3981,"lng":-56.8579,"energy_fJ":54.3,"sat":"g19","age_sec":898,"type":"flash"},{"lat":-28.7005,"lng":-54.9657,"energy_fJ":53.3,"sat":"g19","age_sec":900,"type":"flash"},{"lat":-28.8864,"lng":-56.0609,"energy_fJ":52.3,"sat":"g19","age_sec":898,"type":"flash"},{"lat":10.3351,"lng":-81.8828,"energy_fJ":50.3,"sat":"g18","age_sec":899,"type":"flash"},{"lat":35.0169,"lng":-73.0497,"energy_fJ":46.3,"sat":"g19","age_sec":898,"type":"flash"},{"lat":47.733,"lng":-86.2754,"energy_fJ":44.3,"sat":"g19","age_sec":899,"type":"flash"},{"lat":-29.0817,"lng":-57.4071,"energy_fJ":42.3,"sat":"g19","age_sec":900,"type":"flash"},{"lat":9.7987,"lng":-77.9281,"energy_fJ":39.3,"sat":"g19","age_sec":898,"type":"flash"},{"lat":-28.3552,"lng":-55.2231,"energy_fJ":37.3,"sat":"g19","age_sec":899,"type":"flash"},{"lat":-30.2031,"lng":-57.2832,"energy_fJ":37.3,"sat":"g19","age_sec":898,"type":"flash"},{"lat":50.1398,"lng":-89.1203,"energy_fJ":36.3,"sat":"g19","age_sec":900,"type":"flash"},{"lat":28.1548,"lng":-89.2643,"energy_fJ":35.3,"sat":"g19","age_sec":900,"type":"flash"},{"lat":28.8295,"lng":-89.5253,"energy_fJ":33.3,"sat":"g18","age_sec":898,"type":"flash"},{"lat":-29.4534,"lng":-58.0461,"energy_fJ":31.3,"sat":"g19","age_sec":898,"type":"flash"},{"lat":51.1774,"lng":-92.1014,"energy_fJ":31.3,"sat":"g19","age_sec":897,"type":"flash"},{"lat":28.8573,"lng":-89.6461,"energy_fJ":30.3,"sat":"g19","age_sec":900,"type":"flash"},{"lat":-28.9406,"lng":-56.1422,"energy_fJ":30.3,"sat":"g19","age_sec":899,"type":"flash"},{"lat":27.1592,"lng":166.3737,"energy_fJ":29.3,"sat":"g18","age_sec":897,"type":"flash"},{"lat":7.8512,"lng":-73.552,"energy_fJ":27.3,"sat":"g19","age_sec":897,"type":"flash"},{"lat":27.1593,"lng":166.3739,"energy_fJ":27.3,"sat":"g18","age_sec":900,"type":"flash"},{"lat":17.1664,"lng":-109.234,"energy_fJ":25.3,"sat":"g19","age_sec":897,"type":"flash"},{"lat":28.1489,"lng":-89.1531,"energy_fJ":25.3,"sat":"g18","age_sec":900,"type":"flash"},{"lat":-28.8932,"lng":-56.2449,"energy_fJ":24.3,"sat":"g19","age_sec":897,"type":"flash"},{"lat":-29.7603,"lng":-55.0273,"energy_fJ":21.3,"sat":"g19","age_sec":898,"type":"flash"},{"lat":44.7939,"lng":-95.2923,"energy_fJ":21.3,"sat":"g18","age_sec":899,"type":"flash"},{"lat":-28.1593,"lng":-56.9859,"energy_fJ":20.3,"sat":"g19","age_sec":898,"type":"flash"},{"lat":50.0816,"lng":-91.9101,"energy_fJ":15.3,"sat":"g19","age_sec":899,"type":"flash"},{"lat":-28.1449,"lng":-55.3106,"energy_fJ":15.3,"sat":"g19","age_sec":898,"type":"flash"},{"lat":-29.0514,"lng":-57.4009,"energy_fJ":15.3,"sat":"g19","age_sec":898,"type":"flash"},{"lat":44.8283,"lng":-95.5044,"energy_fJ":14.3,"sat":"g19","age_sec":899,"type":"flash"},{"lat":28.1509,"lng":-89.185,"energy_fJ":13.3,"sat":"g19","age_sec":898,"type":"flash"},{"lat":-29.4624,"lng":-51.9294,"energy_fJ":11.3,"sat":"g19","age_sec":899,"type":"flash"},{"lat":-28.7236,"lng":-54.9909,"energy_fJ":11.3,"sat":"g19","age_sec":897,"type":"flash"},{"lat":46.0232,"lng":-97.1179,"energy_fJ":10.3,"sat":"g19","age_sec":897,"type":"flash"},{"lat":28.8475,"lng":-89.4941,"energy_fJ":10.3,"sat":"g18","age_sec":900,"type":"flash"},{"lat":-28.1842,"lng":-56.3092,"energy_fJ":9.3,"sat":"g19","age_sec":898,"type":"flash"},{"lat":25.8598,"lng":-87.3098,"energy_fJ":9.3,"sat":"g19","age_sec":897,"type":"flash"},{"lat":45.0438,"lng":-98.9646,"energy_fJ":8.3,"sat":"g19","age_sec":898,"type":"flash"},{"lat":35.4985,"lng":-74.0075,"energy_fJ":8.3,"sat":"g19","age_sec":898,"type":"flash"},{"lat":35.0672,"lng":-73.3259,"energy_fJ":8.3,"sat":"g19","age_sec":897,"type":"flash"},{"lat":46.015,"lng":-96.9911,"energy_fJ":7.3,"sat":"g19","age_sec":900,"type":"flash"},{"lat":35.7936,"lng":-74.0039,"energy_fJ":7.3,"sat":"g19","age_sec":898,"type":"flash"},{"lat":-29.0141,"lng":-57.4814,"energy_fJ":6.3,"sat":"g19","age_sec":899,"type":"flash"},{"lat":10.3594,"lng":-66.3124,"energy_fJ":3.3,"sat":"g19","age_sec":898,"type":"flash"},{"lat":-29.3374,"lng":-52.9515,"energy_fJ":3.3,"sat":"g19","age_sec":897,"type":"flash"}]}