{"generated_at":"2026-06-05T14:14:42+00:00","window_minutes":15,"counts":{"total":73,"g19":40,"g18":33},"source":"NOAA GOES-R GLM L2 LCFA via NOAA Open Data on AWS S3 (public, no auth)","flashes":[{"lat":-22.6949,"lng":170.0164,"energy_fJ":2389.3,"sat":"g18","age_sec":900,"type":"flash"},{"lat":42.9385,"lng":-161.8402,"energy_fJ":1981.3,"sat":"g18","age_sec":897,"type":"flash"},{"lat":-20.5035,"lng":169.3962,"energy_fJ":1959.3,"sat":"g18","age_sec":898,"type":"flash"},{"lat":23.0296,"lng":-78.8605,"energy_fJ":1936.3,"sat":"g18","age_sec":891,"type":"flash"},{"lat":-20.567,"lng":169.3654,"energy_fJ":1281.3,"sat":"g18","age_sec":887,"type":"flash"},{"lat":-24.1982,"lng":173.5858,"energy_fJ":904.3,"sat":"g18","age_sec":896,"type":"flash"},{"lat":-22.8723,"lng":169.3262,"energy_fJ":896.3,"sat":"g18","age_sec":890,"type":"flash"},{"lat":9.2506,"lng":-75.5813,"energy_fJ":515.3,"sat":"g19","age_sec":889,"type":"flash"},{"lat":14.8539,"lng":-95.5015,"energy_fJ":419.3,"sat":"g18","age_sec":887,"type":"flash"},{"lat":-21.318,"lng":-121.7702,"energy_fJ":371.3,"sat":"g19","age_sec":899,"type":"flash"},{"lat":-21.3188,"lng":-121.7701,"energy_fJ":364.3,"sat":"g19","age_sec":896,"type":"flash"},{"lat":-20.4638,"lng":169.3557,"energy_fJ":363.3,"sat":"g18","age_sec":884,"type":"flash"},{"lat":-17.2985,"lng":165.6914,"energy_fJ":362.3,"sat":"g18","age_sec":888,"type":"flash"},{"lat":9.1765,"lng":-74.8902,"energy_fJ":356.3,"sat":"g19","age_sec":888,"type":"flash"},{"lat":-21.3191,"lng":-121.7718,"energy_fJ":347.3,"sat":"g19","age_sec":885,"type":"flash"},{"lat":-20.5139,"lng":169.3776,"energy_fJ":340.3,"sat":"g18","age_sec":889,"type":"flash"},{"lat":-21.319,"lng":-121.77,"energy_fJ":315.3,"sat":"g19","age_sec":888,"type":"flash"},{"lat":-21.3182,"lng":-121.769,"energy_fJ":309.3,"sat":"g19","age_sec":893,"type":"flash"},{"lat":-21.3184,"lng":-121.7689,"energy_fJ":289.3,"sat":"g19","age_sec":890,"type":"flash"},{"lat":-21.3194,"lng":-121.771,"energy_fJ":286.3,"sat":"g19","age_sec":887,"type":"flash"},{"lat":-21.3186,"lng":-121.7699,"energy_fJ":263.3,"sat":"g19","age_sec":895,"type":"flash"},{"lat":14.8592,"lng":-95.4299,"energy_fJ":232.3,"sat":"g19","age_sec":887,"type":"flash"},{"lat":-20.5297,"lng":169.3446,"energy_fJ":210.3,"sat":"g18","age_sec":895,"type":"flash"},{"lat":19.236,"lng":-102.719,"energy_fJ":203.3,"sat":"g19","age_sec":893,"type":"flash"},{"lat":-21.3182,"lng":-121.7707,"energy_fJ":199.3,"sat":"g19","age_sec":898,"type":"flash"},{"lat":9.2942,"lng":-90.7798,"energy_fJ":196.3,"sat":"g19","age_sec":899,"type":"flash"},{"lat":23.0521,"lng":-78.7619,"energy_fJ":196.3,"sat":"g19","age_sec":891,"type":"flash"},{"lat":19.2419,"lng":-102.6534,"energy_fJ":189.3,"sat":"g18","age_sec":893,"type":"flash"},{"lat":21.9204,"lng":-97.7859,"energy_fJ":187.3,"sat":"g19","age_sec":900,"type":"flash"},{"lat":21.934,"lng":-97.738,"energy_fJ":175.3,"sat":"g18","age_sec":900,"type":"flash"},{"lat":20.8387,"lng":-98.7041,"energy_fJ":158.3,"sat":"g18","age_sec":899,"type":"flash"},{"lat":-1.7016,"lng":-59.8186,"energy_fJ":151.3,"sat":"g19","age_sec":883,"type":"flash"},{"lat":9.2814,"lng":-90.7218,"energy_fJ":143.3,"sat":"g18","age_sec":899,"type":"flash"},{"lat":-1.6525,"lng":-57.7511,"energy_fJ":120.3,"sat":"g19","age_sec":890,"type":"flash"},{"lat":19.1418,"lng":-102.3633,"energy_fJ":114.3,"sat":"g19","age_sec":889,"type":"flash"},{"lat":-22.7036,"lng":170.8247,"energy_fJ":110.3,"sat":"g18","age_sec":896,"type":"flash"},{"lat":-20.5254,"lng":169.2685,"energy_fJ":109.3,"sat":"g18","age_sec":891,"type":"flash"},{"lat":24.3292,"lng":-77.6371,"energy_fJ":107.3,"sat":"g19","age_sec":891,"type":"flash"},{"lat":20.8438,"lng":-98.6814,"energy_fJ":99.3,"sat":"g19","age_sec":899,"type":"flash"},{"lat":-21.3181,"lng":-121.7694,"energy_fJ":80.3,"sat":"g19","age_sec":892,"type":"flash"},{"lat":42.4534,"lng":-99.5756,"energy_fJ":76.3,"sat":"g18","age_sec":888,"type":"flash"},{"lat":-19.673,"lng":168.3231,"energy_fJ":71.3,"sat":"g18","age_sec":888,"type":"flash"},{"lat":14.511,"lng":-104.2993,"energy_fJ":70.3,"sat":"g18","age_sec":889,"type":"flash"},{"lat":11.4513,"lng":-89.2301,"energy_fJ":66.3,"sat":"g19","age_sec":894,"type":"flash"},{"lat":19.213,"lng":-102.6268,"energy_fJ":63.3,"sat":"g19","age_sec":899,"type":"flash"},{"lat":-21.318,"lng":-121.7692,"energy_fJ":51.3,"sat":"g19","age_sec":891,"type":"flash"},{"lat":42.3967,"lng":-99.5122,"energy_fJ":49.3,"sat":"g19","age_sec":888,"type":"flash"},{"lat":11.4571,"lng":-89.1292,"energy_fJ":46.3,"sat":"g18","age_sec":894,"type":"flash"},{"lat":-19.5011,"lng":167.8281,"energy_fJ":44.3,"sat":"g18","age_sec":899,"type":"flash"},{"lat":14.4868,"lng":-104.3238,"energy_fJ":42.3,"sat":"g19","age_sec":889,"type":"flash"},{"lat":19.1567,"lng":-102.3275,"energy_fJ":42.3,"sat":"g18","age_sec":889,"type":"flash"},{"lat":9.5723,"lng":-78.3943,"energy_fJ":40.3,"sat":"g19","age_sec":889,"type":"flash"},{"lat":-1.2882,"lng":-57.7312,"energy_fJ":37.3,"sat":"g19","age_sec":899,"type":"flash"},{"lat":18.354,"lng":-103.6662,"energy_fJ":25.3,"sat":"g19","age_sec":893,"type":"flash"},{"lat":54.2116,"lng":-117.3166,"energy_fJ":25.3,"sat":"g18","age_sec":889,"type":"flash"},{"lat":10.9678,"lng":-81.1756,"energy_fJ":24.3,"sat":"g19","age_sec":893,"type":"flash"},{"lat":-2.1705,"lng":-56.9462,"energy_fJ":20.3,"sat":"g19","age_sec":894,"type":"flash"},{"lat":-2.5304,"lng":-57.9555,"energy_fJ":16.3,"sat":"g19","age_sec":894,"type":"flash"},{"lat":-22.712,"lng":170.0981,"energy_fJ":16.3,"sat":"g18","age_sec":899,"type":"flash"},{"lat":-12.3377,"lng":170.378,"energy_fJ":16.3,"sat":"g18","age_sec":890,"type":"flash"},{"lat":-23.1832,"lng":170.9102,"energy_fJ":15.3,"sat":"g18","age_sec":886,"type":"flash"},{"lat":9.3931,"lng":-75.4641,"energy_fJ":14.3,"sat":"g19","age_sec":892,"type":"flash"},{"lat":13.7316,"lng":-83.6152,"energy_fJ":13.3,"sat":"g19","age_sec":896,"type":"flash"},{"lat":19.2263,"lng":-102.5514,"energy_fJ":13.3,"sat":"g18","age_sec":899,"type":"flash"},{"lat":18.3563,"lng":-103.5568,"energy_fJ":13.3,"sat":"g18","age_sec":893,"type":"flash"},{"lat":-20.4592,"lng":169.4388,"energy_fJ":13.3,"sat":"g18","age_sec":893,"type":"flash"},{"lat":23.7083,"lng":-97.5717,"energy_fJ":12.3,"sat":"g19","age_sec":895,"type":"flash"},{"lat":11.2367,"lng":-89.1616,"energy_fJ":12.3,"sat":"g19","age_sec":893,"type":"flash"},{"lat":3.5381,"lng":-127.944,"energy_fJ":10.3,"sat":"g19","age_sec":889,"type":"flash"},{"lat":-19.6596,"lng":168.289,"energy_fJ":10.3,"sat":"g18","age_sec":888,"type":"flash"},{"lat":3.5382,"lng":-127.9459,"energy_fJ":9.3,"sat":"g19","age_sec":898,"type":"flash"},{"lat":-23.9707,"lng":172.951,"energy_fJ":7.3,"sat":"g18","age_sec":884,"type":"flash"},{"lat":3.5372,"lng":-127.9454,"energy_fJ":6.3,"sat":"g19","age_sec":886,"type":"flash"}]}